<gamedata>
  <store>
    <name>Blacksmith</name>
    <baseStoreCost>4.5</baseStoreCost>
    <baseStoreProfit>5</baseStoreProfit> 
    <storeCount>0</storeCount>
    <storeMultiplier>1.15</storeMultiplier>
    <unlockRequirements>0</unlockRequirements>
    <storeUnlocked>false</storeUnlocked>
    <storeTimer>3</storeTimer>
    <image>blacksmith</image>
    <storeExp>1</storeExp>
  </store>
  <store>
    <name>JewelCrafter</name>
    <baseStoreCost>5.111</baseStoreCost>
    <baseStoreProfit>15</baseStoreProfit>
    <storeCount>0</storeCount>
    <storeMultiplier>1.15</storeMultiplier>
    <unlockRequirements>0</unlockRequirements>
    <storeUnlocked>false</storeUnlocked>
    <storeTimer>5</storeTimer>
    <image>jewelcrafter</image>
    <storeExp>1</storeExp>
  </store>
  <store>
      <name>Miner</name>
      <baseStoreCost>5.111</baseStoreCost>
      <baseStoreProfit>15</baseStoreProfit>
      <storeCount>0</storeCount>
      <storeMultiplier>1.15</storeMultiplier>
      <unlockRequirements>0</unlockRequirements>
      <storeUnlocked>false</storeUnlocked>
      <storeTimer>5</storeTimer>
      <image>miner</image>
      <storeExp>1</storeExp>
    </store>
  <store>
      <name>Herbalist</name>
      <baseStoreCost>5.111</baseStoreCost>
      <baseStoreProfit>15</baseStoreProfit>
      <storeCount>0</storeCount>
      <storeMultiplier>1.15</storeMultiplier>
      <unlockRequirements>0</unlockRequirements>
      <storeUnlocked>false</storeUnlocked>
      <storeTimer>5</storeTimer>
      <image>herbalist</image>
      <storeExp>1</storeExp>
    </store>
  <store>
      <name>Hunter</name>
      <baseStoreCost>5.111</baseStoreCost>
      <baseStoreProfit>15</baseStoreProfit>
      <storeCount>0</storeCount>
      <storeMultiplier>1.15</storeMultiplier>
      <unlockRequirements>0</unlockRequirements>
      <storeUnlocked>false</storeUnlocked>
      <storeTimer>5</storeTimer>
      <image>hunter</image>
      <storeExp>1</storeExp>
    </store>
  <store>
      <name>Healer</name>
      <baseStoreCost>5.111</baseStoreCost>
      <baseStoreProfit>15</baseStoreProfit>
      <storeCount>0</storeCount>
      <storeMultiplier>1.15</storeMultiplier>
      <unlockRequirements>0</unlockRequirements>
      <storeUnlocked>false</storeUnlocked>
      <storeTimer>5</storeTimer>
      <image>healer</image>
      <storeExp>1</storeExp>
    </store>
  <store>
      <name>Archanist</name>
      <baseStoreCost>5.111</baseStoreCost>
      <baseStoreProfit>15</baseStoreProfit>
      <storeCount>0</storeCount>
      <storeMultiplier>1.15</storeMultiplier>
      <unlockRequirements>0</unlockRequirements>
      <storeUnlocked>false</storeUnlocked>
      <storeTimer>5</storeTimer>
      <image>archanist</image>
      <storeExp>1</storeExp>
    </store>
  <store>
      <name>Sage</name>
      <baseStoreCost>5.111</baseStoreCost>
      <baseStoreProfit>15</baseStoreProfit>
      <storeCount>0</storeCount>
      <storeMultiplier>1.15</storeMultiplier>
      <unlockRequirements>0</unlockRequirements>
      <storeUnlocked>false</storeUnlocked>
      <storeTimer>5</storeTimer>  
      <image>sage</image>
      <storeExp>1</storeExp>
    </store>
  <store>
      <name>Alchemist</name>
      <baseStoreCost>5.111</baseStoreCost>
      <baseStoreProfit>15</baseStoreProfit>
      <storeCount>0</storeCount>
      <storeMultiplier>1.15</storeMultiplier>
      <unlockRequirements>0</unlockRequirements>
      <storeUnlocked>false</storeUnlocked>
      <storeTimer>5</storeTimer>
      <image>alchemist</image>
      <storeExp>1</storeExp>
    </store>
</gamedata>
  
